<annotation>
	<folder></folder>
	<filename>151_jpg.rf.ccf2d3fed000f29de9cb630bcd84b6af.jpg</filename>
	<path>151_jpg.rf.ccf2d3fed000f29de9cb630bcd84b6af.jpg</path>
	<source>
		<database>roboflow.ai</database>
	</source>
	<size>
		<width>512</width>
		<height>512</height>
		<depth>3</depth>
	</size>
	<segmented>0</segmented>
	<object>
		<name>car</name>
		<pose>Unspecified</pose>
		<truncated>0</truncated>
		<difficult>0</difficult>
		<occluded>0</occluded>
		<bndbox>
			<xmin>138</xmin>
			<xmax>244</xmax>
			<ymin>172</ymin>
			<ymax>253</ymax>
		</bndbox>
	</object>
	<object>
		<name>bicycle</name>
		<pose>Unspecified</pose>
		<truncated>0</truncated>
		<difficult>0</difficult>
		<occluded>0</occluded>
		<bndbox>
			<xmin>262</xmin>
			<xmax>268</xmax>
			<ymin>177</ymin>
			<ymax>198</ymax>
		</bndbox>
	</object>
	<object>
		<name>auto rickshaw</name>
		<pose>Unspecified</pose>
		<truncated>0</truncated>
		<difficult>0</difficult>
		<occluded>0</occluded>
		<bndbox>
			<xmin>274</xmin>
			<xmax>281</xmax>
			<ymin>176</ymin>
			<ymax>190</ymax>
		</bndbox>
	</object>
	<object>
		<name>auto rickshaw</name>
		<pose>Unspecified</pose>
		<truncated>0</truncated>
		<difficult>0</difficult>
		<occluded>0</occluded>
		<bndbox>
			<xmin>285</xmin>
			<xmax>292</xmax>
			<ymin>176</ymin>
			<ymax>191</ymax>
		</bndbox>
	</object>
	<object>
		<name>rickshaw</name>
		<pose>Unspecified</pose>
		<truncated>0</truncated>
		<difficult>0</difficult>
		<occluded>0</occluded>
		<bndbox>
			<xmin>300</xmin>
			<xmax>308</xmax>
			<ymin>175</ymin>
			<ymax>192</ymax>
		</bndbox>
	</object>
	<object>
		<name>rickshaw</name>
		<pose>Unspecified</pose>
		<truncated>0</truncated>
		<difficult>0</difficult>
		<occluded>0</occluded>
		<bndbox>
			<xmin>324</xmin>
			<xmax>341</xmax>
			<ymin>174</ymin>
			<ymax>201</ymax>
		</bndbox>
	</object>
	<object>
		<name>truck</name>
		<pose>Unspecified</pose>
		<truncated>0</truncated>
		<difficult>0</difficult>
		<occluded>0</occluded>
		<bndbox>
			<xmin>317</xmin>
			<xmax>332</xmax>
			<ymin>172</ymin>
			<ymax>190</ymax>
		</bndbox>
	</object>
	<object>
		<name>bicycle</name>
		<pose>Unspecified</pose>
		<truncated>0</truncated>
		<difficult>0</difficult>
		<occluded>0</occluded>
		<bndbox>
			<xmin>118</xmin>
			<xmax>141</xmax>
			<ymin>179</ymin>
			<ymax>196</ymax>
		</bndbox>
	</object>
</annotation>
