<annotation>
	<folder>train</folder>
	<filename>201_png.rf.f085ccb487bcbce555c84d4ef554d905.jpg</filename>
	<path>/home/istiak/Codes/dhaka_ai/dataset/train2/train/201_png.rf.f085ccb487bcbce555c84d4ef554d905.jpg</path>
	<source>
		<database>Unknown</database>
	</source>
	<size>
		<width>512</width>
		<height>512</height>
		<depth>3</depth>
	</size>
	<segmented>0</segmented>
	<object>
		<name>bus</name>
		<pose>Unspecified</pose>
		<truncated>1</truncated>
		<difficult>0</difficult>
		<bndbox>
			<xmin>1</xmin>
			<ymin>11</ymin>
			<xmax>138</xmax>
			<ymax>399</ymax>
		</bndbox>
	</object>
	<object>
		<name>van</name>
		<pose>Unspecified</pose>
		<truncated>0</truncated>
		<difficult>0</difficult>
		<bndbox>
			<xmin>136</xmin>
			<ymin>193</ymin>
			<xmax>294</xmax>
			<ymax>466</ymax>
		</bndbox>
	</object>
	<object>
		<name>pickup</name>
		<pose>Unspecified</pose>
		<truncated>0</truncated>
		<difficult>0</difficult>
		<bndbox>
			<xmin>323</xmin>
			<ymin>157</ymin>
			<xmax>460</xmax>
			<ymax>372</ymax>
		</bndbox>
	</object>
	<object>
		<name>rickshaw</name>
		<pose>Unspecified</pose>
		<truncated>0</truncated>
		<difficult>0</difficult>
		<bndbox>
			<xmin>277</xmin>
			<ymin>188</ymin>
			<xmax>318</xmax>
			<ymax>342</ymax>
		</bndbox>
	</object>
	<object>
		<name>suv</name>
		<pose>Unspecified</pose>
		<truncated>1</truncated>
		<difficult>0</difficult>
		<bndbox>
			<xmin>480</xmin>
			<ymin>199</ymin>
			<xmax>512</xmax>
			<ymax>245</ymax>
		</bndbox>
	</object>
	<object>
		<name>bus</name>
		<pose>Unspecified</pose>
		<truncated>0</truncated>
		<difficult>0</difficult>
		<bndbox>
			<xmin>288</xmin>
			<ymin>164</ymin>
			<xmax>320</xmax>
			<ymax>200</ymax>
		</bndbox>
	</object>
	<object>
		<name>bus</name>
		<pose>Unspecified</pose>
		<truncated>0</truncated>
		<difficult>0</difficult>
		<bndbox>
			<xmin>269</xmin>
			<ymin>167</ymin>
			<xmax>288</xmax>
			<ymax>184</ymax>
		</bndbox>
	</object>
	<object>
		<name>rickshaw</name>
		<pose>Unspecified</pose>
		<truncated>0</truncated>
		<difficult>0</difficult>
		<bndbox>
			<xmin>458</xmin>
			<ymin>191</ymin>
			<xmax>475</xmax>
			<ymax>240</ymax>
		</bndbox>
	</object>
</annotation>
