<annotation>
	<folder>train</folder>
	<filename>Asraf_27_jpg.rf.808fe6b6dba46acc275a3d8710acc6cf.jpg</filename>
	<path>/home/istiak/Codes/dhaka_ai/dataset/train2/train/Asraf_27_jpg.rf.808fe6b6dba46acc275a3d8710acc6cf.jpg</path>
	<source>
		<database>Unknown</database>
	</source>
	<size>
		<width>512</width>
		<height>512</height>
		<depth>3</depth>
	</size>
	<segmented>0</segmented>
	<object>
		<name>bus</name>
		<pose>Unspecified</pose>
		<truncated>0</truncated>
		<difficult>0</difficult>
		<bndbox>
			<xmin>70</xmin>
			<ymin>36</ymin>
			<xmax>148</xmax>
			<ymax>84</ymax>
		</bndbox>
	</object>
	<object>
		<name>bus</name>
		<pose>Unspecified</pose>
		<truncated>0</truncated>
		<difficult>0</difficult>
		<bndbox>
			<xmin>287</xmin>
			<ymin>23</ymin>
			<xmax>488</xmax>
			<ymax>149</ymax>
		</bndbox>
	</object>
	<object>
		<name>bus</name>
		<pose>Unspecified</pose>
		<truncated>1</truncated>
		<difficult>0</difficult>
		<bndbox>
			<xmin>427</xmin>
			<ymin>2</ymin>
			<xmax>512</xmax>
			<ymax>510</ymax>
		</bndbox>
	</object>
	<object>
		<name>bus</name>
		<pose>Unspecified</pose>
		<truncated>0</truncated>
		<difficult>0</difficult>
		<bndbox>
			<xmin>202</xmin>
			<ymin>6</ymin>
			<xmax>297</xmax>
			<ymax>64</ymax>
		</bndbox>
	</object>
	<object>
		<name>bus</name>
		<pose>Unspecified</pose>
		<truncated>0</truncated>
		<difficult>0</difficult>
		<bndbox>
			<xmin>199</xmin>
			<ymin>46</ymin>
			<xmax>292</xmax>
			<ymax>106</ymax>
		</bndbox>
	</object>
	<object>
		<name>car</name>
		<pose>Unspecified</pose>
		<truncated>1</truncated>
		<difficult>0</difficult>
		<bndbox>
			<xmin>86</xmin>
			<ymin>192</ymin>
			<xmax>440</xmax>
			<ymax>512</ymax>
		</bndbox>
	</object>
	<object>
		<name>van</name>
		<pose>Unspecified</pose>
		<truncated>0</truncated>
		<difficult>0</difficult>
		<bndbox>
			<xmin>173</xmin>
			<ymin>78</ymin>
			<xmax>287</xmax>
			<ymax>120</ymax>
		</bndbox>
	</object>
	<object>
		<name>van</name>
		<pose>Unspecified</pose>
		<truncated>0</truncated>
		<difficult>0</difficult>
		<bndbox>
			<xmin>139</xmin>
			<ymin>69</ymin>
			<xmax>186</xmax>
			<ymax>99</ymax>
		</bndbox>
	</object>
	<object>
		<name>three wheelers (CNG)</name>
		<pose>Unspecified</pose>
		<truncated>0</truncated>
		<difficult>0</difficult>
		<bndbox>
			<xmin>2</xmin>
			<ymin>105</ymin>
			<xmax>112</xmax>
			<ymax>269</ymax>
		</bndbox>
	</object>
	<object>
		<name>three wheelers (CNG)</name>
		<pose>Unspecified</pose>
		<truncated>0</truncated>
		<difficult>0</difficult>
		<bndbox>
			<xmin>58</xmin>
			<ymin>126</ymin>
			<xmax>231</xmax>
			<ymax>344</ymax>
		</bndbox>
	</object>
	<object>
		<name>three wheelers (CNG)</name>
		<pose>Unspecified</pose>
		<truncated>0</truncated>
		<difficult>0</difficult>
		<bndbox>
			<xmin>234</xmin>
			<ymin>126</ymin>
			<xmax>323</xmax>
			<ymax>228</ymax>
		</bndbox>
	</object>
	<object>
		<name>three wheelers (CNG)</name>
		<pose>Unspecified</pose>
		<truncated>0</truncated>
		<difficult>0</difficult>
		<bndbox>
			<xmin>349</xmin>
			<ymin>127</ymin>
			<xmax>418</xmax>
			<ymax>260</ymax>
		</bndbox>
	</object>
	<object>
		<name>three wheelers (CNG)</name>
		<pose>Unspecified</pose>
		<truncated>0</truncated>
		<difficult>0</difficult>
		<bndbox>
			<xmin>392</xmin>
			<ymin>104</ymin>
			<xmax>447</xmax>
			<ymax>236</ymax>
		</bndbox>
	</object>
	<object>
		<name>three wheelers (CNG)</name>
		<pose>Unspecified</pose>
		<truncated>0</truncated>
		<difficult>0</difficult>
		<bndbox>
			<xmin>298</xmin>
			<ymin>105</ymin>
			<xmax>347</xmax>
			<ymax>206</ymax>
		</bndbox>
	</object>
	<object>
		<name>three wheelers (CNG)</name>
		<pose>Unspecified</pose>
		<truncated>0</truncated>
		<difficult>0</difficult>
		<bndbox>
			<xmin>304</xmin>
			<ymin>97</ymin>
			<xmax>370</xmax>
			<ymax>170</ymax>
		</bndbox>
	</object>
	<object>
		<name>three wheelers (CNG)</name>
		<pose>Unspecified</pose>
		<truncated>0</truncated>
		<difficult>0</difficult>
		<bndbox>
			<xmin>187</xmin>
			<ymin>99</ymin>
			<xmax>266</xmax>
			<ymax>203</ymax>
		</bndbox>
	</object>
	<object>
		<name>three wheelers (CNG)</name>
		<pose>Unspecified</pose>
		<truncated>0</truncated>
		<difficult>0</difficult>
		<bndbox>
			<xmin>113</xmin>
			<ymin>90</ymin>
			<xmax>184</xmax>
			<ymax>140</ymax>
		</bndbox>
	</object>
	<object>
		<name>three wheelers (CNG)</name>
		<pose>Unspecified</pose>
		<truncated>0</truncated>
		<difficult>0</difficult>
		<bndbox>
			<xmin>107</xmin>
			<ymin>72</ymin>
			<xmax>140</xmax>
			<ymax>104</ymax>
		</bndbox>
	</object>
	<object>
		<name>three wheelers (CNG)</name>
		<pose>Unspecified</pose>
		<truncated>0</truncated>
		<difficult>0</difficult>
		<bndbox>
			<xmin>239</xmin>
			<ymin>107</ymin>
			<xmax>314</xmax>
			<ymax>202</ymax>
		</bndbox>
	</object>
	<object>
		<name>three wheelers (CNG)</name>
		<pose>Unspecified</pose>
		<truncated>1</truncated>
		<difficult>0</difficult>
		<bndbox>
			<xmin>1</xmin>
			<ymin>80</ymin>
			<xmax>25</xmax>
			<ymax>108</ymax>
		</bndbox>
	</object>
	<object>
		<name>car</name>
		<pose>Unspecified</pose>
		<truncated>0</truncated>
		<difficult>0</difficult>
		<bndbox>
			<xmin>93</xmin>
			<ymin>74</ymin>
			<xmax>115</xmax>
			<ymax>98</ymax>
		</bndbox>
	</object>
</annotation>
