<annotation>
	<folder></folder>
	<filename>Dipto_ 92_jpg.rf.0e98ca5e7394681b0a72317cae78c76e.jpg</filename>
	<path>Dipto_ 92_jpg.rf.0e98ca5e7394681b0a72317cae78c76e.jpg</path>
	<source>
		<database>roboflow.ai</database>
	</source>
	<size>
		<width>512</width>
		<height>512</height>
		<depth>3</depth>
	</size>
	<segmented>0</segmented>
	<object>
		<name>motorbike</name>
		<pose>Unspecified</pose>
		<truncated>0</truncated>
		<difficult>0</difficult>
		<occluded>0</occluded>
		<bndbox>
			<xmin>113</xmin>
			<xmax>484</xmax>
			<ymin>183</ymin>
			<ymax>513</ymax>
		</bndbox>
	</object>
	<object>
		<name>motorbike</name>
		<pose>Unspecified</pose>
		<truncated>0</truncated>
		<difficult>0</difficult>
		<occluded>0</occluded>
		<bndbox>
			<xmin>33</xmin>
			<xmax>177</xmax>
			<ymin>32</ymin>
			<ymax>465</ymax>
		</bndbox>
	</object>
	<object>
		<name>motorbike</name>
		<pose>Unspecified</pose>
		<truncated>0</truncated>
		<difficult>0</difficult>
		<occluded>0</occluded>
		<bndbox>
			<xmin>237</xmin>
			<xmax>252</xmax>
			<ymin>83</ymin>
			<ymax>154</ymax>
		</bndbox>
	</object>
	<object>
		<name>car</name>
		<pose>Unspecified</pose>
		<truncated>0</truncated>
		<difficult>0</difficult>
		<occluded>0</occluded>
		<bndbox>
			<xmin>277</xmin>
			<xmax>354</xmax>
			<ymin>85</ymin>
			<ymax>209</ymax>
		</bndbox>
	</object>
	<object>
		<name>car</name>
		<pose>Unspecified</pose>
		<truncated>0</truncated>
		<difficult>0</difficult>
		<occluded>0</occluded>
		<bndbox>
			<xmin>419</xmin>
			<xmax>513</xmax>
			<ymin>193</ymin>
			<ymax>495</ymax>
		</bndbox>
	</object>
</annotation>
