<annotation>
	<folder>train</folder>
	<filename>Dipto_850_jpg.rf.0a81c625753b094bbb166d3b54481dad.jpg</filename>
	<path>/home/istiak/Codes/dhaka_ai/dataset/train2/train/Dipto_850_jpg.rf.0a81c625753b094bbb166d3b54481dad.jpg</path>
	<source>
		<database>Unknown</database>
	</source>
	<size>
		<width>512</width>
		<height>512</height>
		<depth>3</depth>
	</size>
	<segmented>0</segmented>
	<object>
		<name>three wheelers (CNG)</name>
		<pose>Unspecified</pose>
		<truncated>0</truncated>
		<difficult>0</difficult>
		<bndbox>
			<xmin>60</xmin>
			<ymin>281</ymin>
			<xmax>95</xmax>
			<ymax>344</ymax>
		</bndbox>
	</object>
	<object>
		<name>three wheelers (CNG)</name>
		<pose>Unspecified</pose>
		<truncated>0</truncated>
		<difficult>0</difficult>
		<bndbox>
			<xmin>146</xmin>
			<ymin>289</ymin>
			<xmax>152</xmax>
			<ymax>302</ymax>
		</bndbox>
	</object>
	<object>
		<name>motorbike</name>
		<pose>Unspecified</pose>
		<truncated>0</truncated>
		<difficult>0</difficult>
		<bndbox>
			<xmin>98</xmin>
			<ymin>299</ymin>
			<xmax>104</xmax>
			<ymax>312</ymax>
		</bndbox>
	</object>
</annotation>
