<annotation>
	<folder></folder>
	<filename>Navid_182_jpg.rf.37d12e8d7015aedf7ce40996353095a0.jpg</filename>
	<path>Navid_182_jpg.rf.37d12e8d7015aedf7ce40996353095a0.jpg</path>
	<source>
		<database>roboflow.ai</database>
	</source>
	<size>
		<width>512</width>
		<height>512</height>
		<depth>3</depth>
	</size>
	<segmented>0</segmented>
	<object>
		<name>minivan</name>
		<pose>Unspecified</pose>
		<truncated>0</truncated>
		<difficult>0</difficult>
		<occluded>0</occluded>
		<bndbox>
			<xmin>143</xmin>
			<xmax>184</xmax>
			<ymin>207</ymin>
			<ymax>288</ymax>
		</bndbox>
	</object>
	<object>
		<name>bus</name>
		<pose>Unspecified</pose>
		<truncated>0</truncated>
		<difficult>0</difficult>
		<occluded>0</occluded>
		<bndbox>
			<xmin>173</xmin>
			<xmax>201</xmax>
			<ymin>143</ymin>
			<ymax>213</ymax>
		</bndbox>
	</object>
	<object>
		<name>truck</name>
		<pose>Unspecified</pose>
		<truncated>0</truncated>
		<difficult>0</difficult>
		<occluded>0</occluded>
		<bndbox>
			<xmin>1</xmin>
			<xmax>119</xmax>
			<ymin>178</ymin>
			<ymax>389</ymax>
		</bndbox>
	</object>
</annotation>
