<annotation>
	<folder>train</folder>
	<filename>Navid_333_jpg.rf.3e7fba4c91a254c1178e42c5df5602f6.jpg</filename>
	<path>/home/istiak/Codes/dhaka_ai/dataset/train2/train/Navid_333_jpg.rf.3e7fba4c91a254c1178e42c5df5602f6.jpg</path>
	<source>
		<database>Unknown</database>
	</source>
	<size>
		<width>512</width>
		<height>512</height>
		<depth>3</depth>
	</size>
	<segmented>0</segmented>
	<object>
		<name>car</name>
		<pose>Unspecified</pose>
		<truncated>1</truncated>
		<difficult>0</difficult>
		<bndbox>
			<xmin>307</xmin>
			<ymin>322</ymin>
			<xmax>504</xmax>
			<ymax>512</ymax>
		</bndbox>
	</object>
	<object>
		<name>car</name>
		<pose>Unspecified</pose>
		<truncated>1</truncated>
		<difficult>0</difficult>
		<bndbox>
			<xmin>157</xmin>
			<ymin>372</ymin>
			<xmax>289</xmax>
			<ymax>512</ymax>
		</bndbox>
	</object>
	<object>
		<name>pickup</name>
		<pose>Unspecified</pose>
		<truncated>0</truncated>
		<difficult>0</difficult>
		<bndbox>
			<xmin>75</xmin>
			<ymin>362</ymin>
			<xmax>190</xmax>
			<ymax>511</ymax>
		</bndbox>
	</object>
	<object>
		<name>minivan</name>
		<pose>Unspecified</pose>
		<truncated>0</truncated>
		<difficult>0</difficult>
		<bndbox>
			<xmin>37</xmin>
			<ymin>377</ymin>
			<xmax>97</xmax>
			<ymax>445</ymax>
		</bndbox>
	</object>
	<object>
		<name>bus</name>
		<pose>Unspecified</pose>
		<truncated>0</truncated>
		<difficult>0</difficult>
		<bndbox>
			<xmin>245</xmin>
			<ymin>352</ymin>
			<xmax>300</xmax>
			<ymax>433</ymax>
		</bndbox>
	</object>
	<object>
		<name>bus</name>
		<pose>Unspecified</pose>
		<truncated>0</truncated>
		<difficult>0</difficult>
		<bndbox>
			<xmin>289</xmin>
			<ymin>354</ymin>
			<xmax>310</xmax>
			<ymax>427</ymax>
		</bndbox>
	</object>
</annotation>
