<annotation>
	<folder>train</folder>
	<filename>Navid_108_jpg.rf.b751827f88f2be93790f8d7dc16952bd.jpg</filename>
	<path>/home/istiak/Codes/dhaka_ai/dataset/train2/train/Navid_108_jpg.rf.b751827f88f2be93790f8d7dc16952bd.jpg</path>
	<source>
		<database>Unknown</database>
	</source>
	<size>
		<width>512</width>
		<height>512</height>
		<depth>3</depth>
	</size>
	<segmented>0</segmented>
	<object>
		<name>rickshaw</name>
		<pose>Unspecified</pose>
		<truncated>0</truncated>
		<difficult>0</difficult>
		<bndbox>
			<xmin>279</xmin>
			<ymin>133</ymin>
			<xmax>337</xmax>
			<ymax>221</ymax>
		</bndbox>
	</object>
	<object>
		<name>car</name>
		<pose>Unspecified</pose>
		<truncated>0</truncated>
		<difficult>0</difficult>
		<bndbox>
			<xmin>250</xmin>
			<ymin>221</ymin>
			<xmax>350</xmax>
			<ymax>325</ymax>
		</bndbox>
	</object>
	<object>
		<name>car</name>
		<pose>Unspecified</pose>
		<truncated>0</truncated>
		<difficult>0</difficult>
		<bndbox>
			<xmin>321</xmin>
			<ymin>295</ymin>
			<xmax>423</xmax>
			<ymax>430</ymax>
		</bndbox>
	</object>
	<object>
		<name>car</name>
		<pose>Unspecified</pose>
		<truncated>1</truncated>
		<difficult>0</difficult>
		<bndbox>
			<xmin>120</xmin>
			<ymin>401</ymin>
			<xmax>242</xmax>
			<ymax>512</ymax>
		</bndbox>
	</object>
	<object>
		<name>car</name>
		<pose>Unspecified</pose>
		<truncated>0</truncated>
		<difficult>0</difficult>
		<bndbox>
			<xmin>41</xmin>
			<ymin>369</ymin>
			<xmax>174</xmax>
			<ymax>511</ymax>
		</bndbox>
	</object>
	<object>
		<name>motorbike</name>
		<pose>Unspecified</pose>
		<truncated>0</truncated>
		<difficult>0</difficult>
		<bndbox>
			<xmin>90</xmin>
			<ymin>339</ymin>
			<xmax>140</xmax>
			<ymax>394</ymax>
		</bndbox>
	</object>
	<object>
		<name>van</name>
		<pose>Unspecified</pose>
		<truncated>0</truncated>
		<difficult>0</difficult>
		<bndbox>
			<xmin>392</xmin>
			<ymin>82</ymin>
			<xmax>505</xmax>
			<ymax>204</ymax>
		</bndbox>
	</object>
	<object>
		<name>minivan</name>
		<pose>Unspecified</pose>
		<truncated>1</truncated>
		<difficult>0</difficult>
		<bndbox>
			<xmin>442</xmin>
			<ymin>156</ymin>
			<xmax>512</xmax>
			<ymax>282</ymax>
		</bndbox>
	</object>
	<object>
		<name>rickshaw</name>
		<pose>Unspecified</pose>
		<truncated>0</truncated>
		<difficult>0</difficult>
		<bndbox>
			<xmin>470</xmin>
			<ymin>14</ymin>
			<xmax>500</xmax>
			<ymax>77</ymax>
		</bndbox>
	</object>
	<object>
		<name>rickshaw</name>
		<pose>Unspecified</pose>
		<truncated>0</truncated>
		<difficult>0</difficult>
		<bndbox>
			<xmin>424</xmin>
			<ymin>46</ymin>
			<xmax>457</xmax>
			<ymax>96</ymax>
		</bndbox>
	</object>
	<object>
		<name>car</name>
		<pose>Unspecified</pose>
		<truncated>1</truncated>
		<difficult>0</difficult>
		<bndbox>
			<xmin>457</xmin>
			<ymin>332</ymin>
			<xmax>512</xmax>
			<ymax>470</ymax>
		</bndbox>
	</object>
</annotation>
