<annotation>
	<folder>train</folder>
	<filename>Navid_615_JPG.rf.52e7d03bdca4d4e58b837c895aff2e33.jpg</filename>
	<path>/home/istiak/Codes/dhaka_ai/dataset/train2/train/Navid_615_JPG.rf.52e7d03bdca4d4e58b837c895aff2e33.jpg</path>
	<source>
		<database>Unknown</database>
	</source>
	<size>
		<width>512</width>
		<height>512</height>
		<depth>3</depth>
	</size>
	<segmented>0</segmented>
	<object>
		<name>motorbike</name>
		<pose>Unspecified</pose>
		<truncated>0</truncated>
		<difficult>0</difficult>
		<bndbox>
			<xmin>430</xmin>
			<ymin>237</ymin>
			<xmax>501</xmax>
			<ymax>287</ymax>
		</bndbox>
	</object>
	<object>
		<name>rickshaw</name>
		<pose>Unspecified</pose>
		<truncated>0</truncated>
		<difficult>0</difficult>
		<bndbox>
			<xmin>181</xmin>
			<ymin>150</ymin>
			<xmax>420</xmax>
			<ymax>465</ymax>
		</bndbox>
	</object>
	<object>
		<name>rickshaw</name>
		<pose>Unspecified</pose>
		<truncated>1</truncated>
		<difficult>0</difficult>
		<bndbox>
			<xmin>1</xmin>
			<ymin>158</ymin>
			<xmax>73</xmax>
			<ymax>512</ymax>
		</bndbox>
	</object>
</annotation>
