<annotation>
	<folder>train</folder>
	<filename>Numan_(491)_jpg.rf.3b684c6ce8c10e29b8201ef3cc53d0c2.jpg</filename>
	<path>/home/istiak/Codes/dhaka_ai/dataset/train2/train/Numan_(491)_jpg.rf.3b684c6ce8c10e29b8201ef3cc53d0c2.jpg</path>
	<source>
		<database>Unknown</database>
	</source>
	<size>
		<width>512</width>
		<height>512</height>
		<depth>3</depth>
	</size>
	<segmented>0</segmented>
	<object>
		<name>car</name>
		<pose>Unspecified</pose>
		<truncated>0</truncated>
		<difficult>0</difficult>
		<bndbox>
			<xmin>168</xmin>
			<ymin>169</ymin>
			<xmax>393</xmax>
			<ymax>250</ymax>
		</bndbox>
	</object>
	<object>
		<name>rickshaw</name>
		<pose>Unspecified</pose>
		<truncated>0</truncated>
		<difficult>0</difficult>
		<bndbox>
			<xmin>75</xmin>
			<ymin>153</ymin>
			<xmax>135</xmax>
			<ymax>209</ymax>
		</bndbox>
	</object>
	<object>
		<name>wheelbarrow</name>
		<pose>Unspecified</pose>
		<truncated>1</truncated>
		<difficult>0</difficult>
		<bndbox>
			<xmin>1</xmin>
			<ymin>182</ymin>
			<xmax>51</xmax>
			<ymax>214</ymax>
		</bndbox>
	</object>
	<object>
		<name>motorbike</name>
		<pose>Unspecified</pose>
		<truncated>0</truncated>
		<difficult>0</difficult>
		<bndbox>
			<xmin>132</xmin>
			<ymin>161</ymin>
			<xmax>176</xmax>
			<ymax>212</ymax>
		</bndbox>
	</object>
	<object>
		<name>three wheelers (CNG)</name>
		<pose>Unspecified</pose>
		<truncated>0</truncated>
		<difficult>0</difficult>
		<bndbox>
			<xmin>55</xmin>
			<ymin>157</ymin>
			<xmax>84</xmax>
			<ymax>195</ymax>
		</bndbox>
	</object>
	<object>
		<name>three wheelers (CNG)</name>
		<pose>Unspecified</pose>
		<truncated>0</truncated>
		<difficult>0</difficult>
		<bndbox>
			<xmin>169</xmin>
			<ymin>160</ymin>
			<xmax>197</xmax>
			<ymax>184</ymax>
		</bndbox>
	</object>
</annotation>
